README.txt
setup.py
financeData/__init__.py
financeData/data.py
financeData/getyahoodata.py
financeData/getyahoodatafx.py
financeData/getyahoostatdata.py
financeData/graph.py
financeData/utils.py
financeData.egg-info/PKG-INFO
financeData.egg-info/SOURCES.txt
financeData.egg-info/dependency_links.txt
financeData.egg-info/requires.txt
financeData.egg-info/top_level.txt