Metadata-Version: 2.1
Name: financeData
Version: 0.0.3
Summary: Basic Data Source For Stock,FX,Coin
Home-page: UNKNOWN
Author: Berkay Coşkun
Author-email: berkayreb@gmail.com
License: MIT
Platform: UNKNOWN
